LICENSE
README.md
setup.py
SNPmanifold/SNPmanifold.py
SNPmanifold/VAE_models.py
SNPmanifold/__init__.py
SNPmanifold/utils_io.py
SNPmanifold/utils_tools.py
SNPmanifold/version.py
SNPmanifold.egg-info/PKG-INFO
SNPmanifold.egg-info/SOURCES.txt
SNPmanifold.egg-info/dependency_links.txt
SNPmanifold.egg-info/requires.txt
SNPmanifold.egg-info/top_level.txt