Metadata-Version: 2.1
Name: SNPmanifold
Version: 0.0.9
Summary: SNPmanifold:  Manifold learning for single-cell SNVs
Home-page: https://github.com/StatBiomed/SNPmanifold
Author: ['Kevin Chung', 'Yuanhua Huang']
Author-email: u3570318@connect.hku.hk
License: Apache-2.0
Keywords: Manifold learning,Variational autoencoder,Single-cell single-nucleotide variations,Phylogenetic reconstruction
License-File: LICENSE
Requires-Dist: anndata>=0.6
Requires-Dist: scanpy
Requires-Dist: leidenalg
Requires-Dist: numpy>=1.18.0
Requires-Dist: scipy>=1.4.1
Requires-Dist: pandas>=0.23.0
Requires-Dist: networkx
Requires-Dist: matplotlib>=3.1.2
Requires-Dist: seaborn>=0.10.0
Requires-Dist: torch
Requires-Dist: scikit-learn>=0.23
Requires-Dist: umap-learn>=0.5.3
Requires-Dist: tqdm
Provides-Extra: docs
Requires-Dist: sphinx_bootstrap_theme; extra == "docs"
